vcard/__init__.py
vcard/vcard.py
vcard/vcard_definitions.py
vcard/vcard_errors.py
vcard/vcard_property.py
vcard/vcard_utils.py
vcard/vcard_validator.py
vcard/vcard_validators.py
vcard-1.0.0.data/data/bash-completion/vcard
vcard-1.0.0.dist-info/LICENSE.txt
vcard-1.0.0.dist-info/METADATA
vcard-1.0.0.dist-info/WHEEL
vcard-1.0.0.dist-info/entry_points.txt
vcard-1.0.0.dist-info/top_level.txt
vcard-1.0.0.dist-info/RECORD
