Metadata-Version: 2.1
Name: vcard
Version: 1.0.0
Summary: vCard validator, class and utility functions
Home-page: https://gitlab.com/engmark/vcard
Download-URL: https://pypi.org/project/vcard/
Author: Victor Engmark
Author-email: victor@engmark.name
Maintainer: Victor Engmark
Maintainer-email: victor@engmark.name
License: AGPLv3
Keywords: vCard vCards RFC 2426 RFC2426 validator
Platform: POSIX
Platform: Windows
Classifier: Development Status :: 4 - Beta
Classifier: Environment :: Console
Classifier: Intended Audience :: End Users/Desktop
Classifier: License :: OSI Approved :: GNU Affero General Public License v3
Classifier: Natural Language :: English
Classifier: Operating System :: OS Independent
Classifier: Programming Language :: Python :: 3.8
Classifier: Programming Language :: Python :: 3.9
Classifier: Programming Language :: Python :: 3.10
Classifier: Programming Language :: Python :: 3.11
Classifier: Programming Language :: Python :: 3.12
Classifier: Programming Language :: Python :: 3.13
Classifier: Topic :: Text Processing
Classifier: Topic :: Utilities
Obsoletes: vcard_module
License-File: LICENSE.txt
Requires-Dist: python-dateutil ~=2.9.0
